causal_time_series-0.0.2.dist-info/licenses/LICENSE
cts/__init__.py
cts/core.py
cts/dag.py
cts/intervene.py
cts/models/__init__.py
cts/models/ridge_delta.py
cts/utils/__init__.py
cts/utils/datasets.py
causal_time_series-0.0.2.dist-info/METADATA
causal_time_series-0.0.2.dist-info/WHEEL
causal_time_series-0.0.2.dist-info/top_level.txt
causal_time_series-0.0.2.dist-info/RECORD
