Metadata-Version: 2.4
Name: causal_time_series
Version: 0.0.2
Summary: Python library for causal time series modeling
Home-page: https://github.com/nikosga/cts/tree/main
Author: Nick Gavriil
License: MIT
Requires-Python: >=3.7
License-File: LICENSE
Requires-Dist: matplotlib
Requires-Dist: pandas
Requires-Dist: numpy
Requires-Dist: scikit-learn
Dynamic: author
Dynamic: description
Dynamic: description-content-type
Dynamic: home-page
Dynamic: license
Dynamic: license-file
Dynamic: requires-dist
Dynamic: requires-python
Dynamic: summary
